handythread/__init__.py
handythread/_handythread.py
handythread3-0.0.2.dist-info/METADATA
handythread3-0.0.2.dist-info/WHEEL
handythread3-0.0.2.dist-info/top_level.txt
handythread3-0.0.2.dist-info/RECORD
